CHANGELOG.txt
LICENCE.txt
MANIFEST.in
README.txt
main.py
requirements.txt
setup.py
classify_image/__init__.py
classify_image/classify.py
classify_image/efficientNet_custom.py
classify_image/efficientnet/__init__.py
classify_image/efficientnet/__version__.py
classify_image/efficientnet/keras.py
classify_image/efficientnet/model.py
classify_image/efficientnet/preprocessing.py
classify_image/efficientnet/tfkeras.py
classify_image/efficientnet/weights.py
extract_video/__init__.py
extract_video/extract_with_cv2.py
extract_video/extract_with_decord.py
image_to_text/__init__.py
image_to_text/config.py
image_to_text/detector_process.py
image_to_text/read_text.py
image_to_text/reader_process.py
image_to_text/craft_text_detector/__init__.py
image_to_text/craft_text_detector/craft_utils.py
image_to_text/craft_text_detector/file_utils.py
image_to_text/craft_text_detector/image_utils.py
image_to_text/craft_text_detector/predict.py
image_to_text/craft_text_detector/torch_utils.py
image_to_text/craft_text_detector/models/__init__.py
image_to_text/craft_text_detector/models/craftnet.py
image_to_text/craft_text_detector/models/refinenet.py
image_to_text/craft_text_detector/models/basenet/__init__.py
image_to_text/craft_text_detector/models/basenet/vgg16_bn.py
image_to_text/src/basenet/__init__.py
image_to_text/src/basenet/vgg16_bn.py
image_to_text/src/char/char.txt
image_to_text/src/char/char_list.txt
image_to_text/src/char/bo/char.txt
image_to_text/src/char/bo/char1.txt
image_to_text/src/char/bo/char_viet_vi_fake.txt
image_to_text/src/deeptext/create_lmdb_dataset.py
image_to_text/src/deeptext/dataset.py
image_to_text/src/deeptext/demo.py
image_to_text/src/deeptext/model.py
image_to_text/src/deeptext/model_resnet.py
image_to_text/src/deeptext/model_vgg.py
image_to_text/src/deeptext/model_vgg_attn.py
image_to_text/src/deeptext/opt.py
image_to_text/src/deeptext/utils.py
image_to_text/src/modules/feature_extraction.py
image_to_text/src/modules/prediction.py
metadata_extraction_vnpt_media.egg-info/PKG-INFO
metadata_extraction_vnpt_media.egg-info/SOURCES.txt
metadata_extraction_vnpt_media.egg-info/dependency_links.txt
metadata_extraction_vnpt_media.egg-info/top_level.txt