Metadata-Version: 2.1
Name: metadata-extraction-vnpt-media
Version: 0.0.1
Summary: metadata extraction
Home-page: 
Author: nntuan
Author-email: ngoctuan.nguyen1202@gmail.com
License: MIT
Keywords: calculator
Classifier: Development Status :: 5 - Production/Stable
Classifier: Intended Audience :: Education
Classifier: Operating System :: Microsoft :: Windows :: Windows 10
Classifier: License :: OSI Approved :: MIT License
Classifier: Programming Language :: Python :: 3
License-File: LICENCE.txt
